CHANGES.txt
MANIFEST.in
README.md
requirements.txt
setup.py
wheelcms_comments/__init__.py
wheelcms_comments/models.py
wheelcms_comments.egg-info/PKG-INFO
wheelcms_comments.egg-info/SOURCES.txt
wheelcms_comments.egg-info/dependency_links.txt
wheelcms_comments.egg-info/namespace_packages.txt
wheelcms_comments.egg-info/not-zip-safe
wheelcms_comments.egg-info/requires.txt
wheelcms_comments.egg-info/top_level.txt
wheelcms_comments/locale/en/LC_MESSAGES/django.mo
wheelcms_comments/locale/en/LC_MESSAGES/django.po
wheelcms_comments/locale/nl/LC_MESSAGES/django.mo
wheelcms_comments/locale/nl/LC_MESSAGES/django.po
wheelcms_comments/migrations/0001_initial.py
wheelcms_comments/migrations/__init__.py
wheelcms_comments/templates/wheelcms_axle/comments.html
wheelcms_comments/templates/wheelcms_comments/comment_view.html
wheelcms_comments/templates/wheelcms_comments/commentform.html
wheelcms_comments/templatetags/__init__.py
wheelcms_comments/templatetags/wheel_comments.py
wheelcms_comments/tests/__init__.py
wheelcms_comments/tests/conftest.py
wheelcms_comments/tests/test_comments.py