Metadata-Version: 1.1
Name: wheelcms-comments
Version: 0.2
Summary: WheelCMS comments package
Home-page: http://github.com/wheelcms/wheelcms_comments
Author: Ivo van der Wijk
Author-email: wheelcms@in.m3r.nl
License: BSD
Platform: UNKNOWN
Classifier: Programming Language :: Python
